rtctools_water_allocation/__init__.py
rtctools_water_allocation/_version.py
rtc_tools_water_allocation-0.0.1.dist-info/COPYING.LESSER
rtc_tools_water_allocation-0.0.1.dist-info/METADATA
rtc_tools_water_allocation-0.0.1.dist-info/WHEEL
rtc_tools_water_allocation-0.0.1.dist-info/top_level.txt
rtc_tools_water_allocation-0.0.1.dist-info/RECORD
