Metadata-Version: 2.1
Name: rtc-tools-water-allocation
Version: 0.0.1
Summary: Water allocation models for RTC-Tools 2.
Home-page: http://www.deltares.nl/en/software/rtc-tools/
Author: Deltares
Maintainer: Jack Vreeken
License: LGPLv3
Keywords: rtctools optimization water allocation
Platform: Windows
Platform: Linux
Platform: Mac OS-X
Platform: Unix
Classifier: Development Status :: 4 - Beta
Classifier: Intended Audience :: Science/Research
Classifier: Intended Audience :: Information Technology
Classifier: License :: OSI Approved :: GNU Lesser General Public License v3 (LGPLv3)
Classifier: Programming Language :: Other
Classifier: Topic :: Scientific/Engineering :: GIS
Classifier: Topic :: Scientific/Engineering :: Mathematics
Classifier: Topic :: Scientific/Engineering :: Physics
Classifier: Operating System :: Microsoft :: Windows
Classifier: Operating System :: POSIX
Classifier: Operating System :: Unix
Classifier: Operating System :: MacOS
Requires-Python: >=3.5
Requires-Dist: rtc-tools (>=2.3.0a2)
Requires-Dist: rtc-tools-channel-flow (==1.*)
Requires-Dist: numpy
Requires-Dist: casadi
